docs/dev/README.md
docs/dev/cli.md
docs/dev/dependencies.md
docs/dev/github.md
docs/dev/pypi.md
docs/dev/settings.md
tests/__init__.py
tests/test_tvdata.py
tvdata/__init__.py
tvdata/_version.py
tvdata/cli.py
tvdata/py.typed
tvdata/settings.py
tvdata/conf/__init__.py
tvdata/conf/settings.py
tvdata/core/__init__.py
tvdata/core/client.py
tvdata-0.2.0.dist-info/licenses/LICENSE
tvdata-0.2.0.dist-info/METADATA
tvdata-0.2.0.dist-info/WHEEL
tvdata-0.2.0.dist-info/entry_points.txt
tvdata-0.2.0.dist-info/top_level.txt
tvdata-0.2.0.dist-info/RECORD
