Metadata-Version: 2.4
Name: tvdata
Version: 0.2.0
Summary: A Python library and CLI for fetching and exporting enormous amounts of financial & candle data without limit.
Author: flolep2607
License: MIT License
Keywords: tradingview,finance,trading,candles,data,cli,pandas,timeframes,tickers
Classifier: Development Status :: 4 - Beta
Classifier: Intended Audience :: Developers
Classifier: Intended Audience :: Financial and Insurance Industry
Classifier: License :: OSI Approved :: MIT License
Classifier: Programming Language :: Python :: 3
Classifier: Programming Language :: Python :: 3.8
Classifier: Programming Language :: Python :: 3.9
Classifier: Programming Language :: Python :: 3.10
Classifier: Programming Language :: Python :: 3.11
Classifier: Operating System :: OS Independent
Classifier: Topic :: Software Development :: Libraries :: Python Modules
Classifier: Topic :: Office/Business :: Financial :: Investment
License-File: LICENSE
Requires-Dist: pydantic~=2.0
Requires-Dist: pydantic-settings
Requires-Dist: click
Requires-Dist: requests
Requires-Dist: pandas==2.2.3
Requires-Dist: aiosseclient
Requires-Dist: tqdm
Provides-Extra: dev
Requires-Dist: build; extra == "dev"
Requires-Dist: dapperdata; extra == "dev"
Requires-Dist: glom; extra == "dev"
Requires-Dist: mypy; extra == "dev"
Requires-Dist: pytest; extra == "dev"
Requires-Dist: pytest-asyncio; extra == "dev"
Requires-Dist: pytest-cov; extra == "dev"
Requires-Dist: pytest-pretty; extra == "dev"
Requires-Dist: ruamel.yaml; extra == "dev"
Requires-Dist: ruff; extra == "dev"
Requires-Dist: toml-sort; extra == "dev"
Requires-Dist: uv; extra == "dev"
Requires-Dist: types-requests; extra == "dev"
Requires-Dist: pandas-stubs; extra == "dev"
Requires-Dist: types-tqdm; extra == "dev"
Dynamic: license-file
